WikiWho/__init__.py
WikiWho/structures.py
WikiWho/utils.py
WikiWho/wikiwho.py
WikiWho/examples/__init__.py
WikiWho/examples/process_api_output.py
WikiWho/examples/process_xml_dump.py
WikiWho-1.0.3.dist-info/LICENSE.txt
WikiWho-1.0.3.dist-info/METADATA
WikiWho-1.0.3.dist-info/WHEEL
WikiWho-1.0.3.dist-info/top_level.txt
WikiWho-1.0.3.dist-info/RECORD
