Metadata-Version: 2.1
Name: WikiWho
Version: 1.0.3
Summary: An algorithm to identify authorship and editor interactions in Wiki revisioned content.
Home-page: https://github.com/wikiwho/WikiWho
Author: UNKNOWN
Author-email: UNKNOWN
License: MIT
Keywords: wikipedia revision content authorship
Platform: UNKNOWN
Classifier: License :: OSI Approved :: MIT License
Classifier: Programming Language :: Python :: 2
Classifier: Programming Language :: Python :: 2.7
Classifier: Programming Language :: Python :: 3
Classifier: Programming Language :: Python :: 3.3
Classifier: Programming Language :: Python :: 3.4
Classifier: Programming Language :: Python :: 3.5
Requires-Dist: requests
Requires-Dist: mwxml
